cspobject/__init__.py
cspobject/obj_test.py
cspobject-0.1.dist-info/DESCRIPTION.rst
cspobject-0.1.dist-info/METADATA
cspobject-0.1.dist-info/RECORD
cspobject-0.1.dist-info/WHEEL
cspobject-0.1.dist-info/metadata.json
cspobject-0.1.dist-info/top_level.txt
