Metadata-Version: 2.0
Name: cspobject
Version: 0.1
Summary: An object-oriented representation of Content Security Policies
Home-page: https://github.com/adambrenecki/cspobject
Author: Adam Brenecki
Author-email: adam@brenecki.id.au
License: MIT
Platform: UNKNOWN
Requires-Dist: attrs (<18,>=17.2.0)
Provides-Extra: dev
Requires-Dist: prospector; extra == 'dev'
Requires-Dist: pytest; extra == 'dev'
